noterrors_sdk/__init__.py
noterrors_sdk/client.py
noterrors_sdk/integrations/__init__.py
noterrors_sdk/integrations/aiohttp.py
noterrors_sdk/integrations/asyncio.py
noterrors_sdk/integrations/base.py
noterrors_sdk/integrations/basic.py
noterrors_sdk/integrations/django.py
noterrors_sdk-0.1.dist-info/METADATA
noterrors_sdk-0.1.dist-info/WHEEL
noterrors_sdk-0.1.dist-info/top_level.txt
noterrors_sdk-0.1.dist-info/RECORD
