Metadata-Version: 2.1
Name: noterrors-sdk
Version: 0.1
Summary: noterrors sdk client
Home-page: https://github.com/jarodut/noterrors-sdk
Author: noterrors
Author-email: jarod@ukr.net
License: UNKNOWN
Platform: UNKNOWN
Classifier: Programming Language :: Python :: 3
Classifier: License :: OSI Approved :: MIT License
Classifier: Operating System :: OS Independent
